{
   "mixins": "stonehearth:mixins:item_properties",
   "type": "entity",
   "components": {
      "model_variants": {
         "default": {
            "models": [
               "file(big_fish_salted_serving.qb)"
            ]
         }
      }
   },
   "entity_data": {
      "stonehearth:item": {
         "category": "food",
         "destroy_on_uncarry": true
      },
      "stonehearth:food": {
         "stonehearth:sitting_on_chair": {
            "satisfaction": 60
         },
         "default": {
            "satisfaction": 40
         },
         "quality": 4
      },
      "stonehearth:catalog": {
         "display_name": "i18n(trapper_plus:food.big_fish_salted_serving.display_name)",
         "description": "",
         "material_tags": [
            "food",
            "big_fish_salted_serving",
            "meat",
            "fish",
            "lunch_time"
         ],
         "subject_override": "trapper_plus:food:big_fish_salted"
      }
   }
}
